.gitignore
LICENSE
MANIFEST.in
README.md
changelog.md
requirements.txt
setup.py
.github/workflows/workflow.yml
docs/.buildinfo
docs/.nojekyll
docs/api.html
docs/genindex.html
docs/index.html
docs/objects.inv
docs/py-modindex.html
docs/search.html
docs/searchindex.js
docs/_sources/api.rst.txt
docs/_sources/index.rst.txt
docs/_sources/generated/simemobilecity.car.Car.get_ident.rst.txt
docs/_sources/generated/simemobilecity.car.Car.get_size.rst.txt
docs/_sources/generated/simemobilecity.car.Car.rst.txt
docs/_sources/generated/simemobilecity.car.Car.set_ident.rst.txt
docs/_sources/generated/simemobilecity.car.Car.set_size.rst.txt
docs/_sources/generated/simemobilecity.mc.MC.add_poi.rst.txt
docs/_sources/generated/simemobilecity.mc.MC.add_user.rst.txt
docs/_sources/generated/simemobilecity.mc.MC.rst.txt
docs/_sources/generated/simemobilecity.mc.MC.run.rst.txt
docs/_sources/generated/simemobilecity.poi.Poi.get_G.rst.txt
docs/_sources/generated/simemobilecity.poi.Poi.get_nodes.rst.txt
docs/_sources/generated/simemobilecity.poi.Poi.get_p.rst.txt
docs/_sources/generated/simemobilecity.poi.Poi.get_p_day.rst.txt
docs/_sources/generated/simemobilecity.poi.Poi.get_p_hour.rst.txt
docs/_sources/generated/simemobilecity.poi.Poi.get_topo.rst.txt
docs/_sources/generated/simemobilecity.poi.Poi.rst.txt
docs/_sources/generated/simemobilecity.poi.Poi.set_p.rst.txt
docs/_sources/generated/simemobilecity.poi.Poi.set_p_day.rst.txt
docs/_sources/generated/simemobilecity.poi.Poi.set_p_hour.rst.txt
docs/_sources/generated/simemobilecity.topology.Topology.charging_station.rst.txt
docs/_sources/generated/simemobilecity.topology.Topology.dist.rst.txt
docs/_sources/generated/simemobilecity.topology.Topology.dist_poi.rst.txt
docs/_sources/generated/simemobilecity.topology.Topology.get_G.rst.txt
docs/_sources/generated/simemobilecity.topology.Topology.get_Gp.rst.txt
docs/_sources/generated/simemobilecity.topology.Topology.get_nodes.rst.txt
simemobilecity.egg-info/PKG-INFO
simemobilecity.egg-info/SOURCES.txt
simemobilecity.egg-info/dependency_links.txt
simemobilecity.egg-info/requires.txt
simemobilecity.egg-info/top_level.txt
