Metadata-Version: 2.1
Name: simemobilecity
Version: 0.1.0
Summary: Charging infrastructure simulation suite.
Home-page: https://github.com/Ajax23/SimeMobileCity
Author: Hamzeh Kraus
Author-email: hamzeh_kraus@web.de
License: UNKNOWN
Platform: UNKNOWN
Classifier: Programming Language :: Python :: 3
Classifier: License :: OSI Approved :: GNU General Public License v3 (GPLv3)
Classifier: Operating System :: OS Independent
Requires-Python: >=3.5
